
{
    "type": "FeatureCollection",
    "name": "malls",
    "crs": { "type": "name", "properties": { "name": "urn:ogc:def:crs:OGC:1.3:CRS84" } },
    "features": [
      {
        "type": "Feature",
        "properties": { "id": 1, "name": "Mall X" },
        "geometry": { "type": "Point", "coordinates": [78.565, 17.46] }
      },
      {
        "type": "Feature",
        "properties": { "id": 2, "name": "Mall Y" },
        "geometry": { "type": "Point", "coordinates": [78.575, 17.455] }
      }
      
    ]
  }
  